{
    "title": "Blueberry Partfait By Vapetasia",
    "brand": "Vapetasia",
    "description": "Enjoy the tart fresh blueberries, creamy yogurt, and crunchy granola flavors. Creamy and sweet combine in a delightful way. Your taste receptors will tingle after tasting this delectable mixture. Vapetasia's Blueberry Parfait dish.",
    "sku": "257306, 257307, 257308, 257309",
    "categories": [
        "SKU:",
        "Brand:",
        "Categories:"
    ],
    "flavors": [],
    "images": [
        "1.jpg",
        "2.jpg"
    ],
    "url": "https://rzsmoke.com/product/blueberry-partfait-by-vapetasia/"
}